Metadata-Version: 2.1
Name: oDrive-calc
Version: 0.0.1
Summary: bldc motor calibration tool
Author: Mario Yprus
License: UNKNOWN
Platform: UNKNOWN
License-File: License.txt
